setup.py
suba/__init__.py
suba/aa.py
test_vipkid_model.egg-info/PKG-INFO
test_vipkid_model.egg-info/SOURCES.txt
test_vipkid_model.egg-info/dependency_links.txt
test_vipkid_model.egg-info/top_level.txt